[
  {
    "module": "account_3way_match",
    "path": "addons/enterprise/account_3way_match",
    "name": "Vendor Bill: Release to Pay",
    "summary": null,
    "version": null,
    "category": "Purchase Management",
    "depends": "purchase",
    "auto_install": null,
    "application": null,
    "license": "OEEL-1",
    "has_qweb": false,
    "has_data": true
  },
  {
    "module": "account_accountant",
    "path": "addons/enterprise/account_accountant",
    "name": "Accounting",
    "summary": "Manage financial and analytic accounting",
    "version": "1.1",
    "category": "Accounting",
    "depends": "account,web_tour",
    "auto_install": false,
    "application": true,
    "license": null,
    "has_qweb": false,
    "has_data": true
  },
  {
    "module": "account_asset",
    "path": "addons/enterprise/account_asset",
    "name": "Assets Management",
    "summary": null,
    "version": null,
    "category": "Accounting",
    "depends": "account",
    "auto_install": null,
    "application": null,
    "license": null,
    "has_qweb": true,
    "has_data": true
  },
  {
    "module": "account_bank_statement_import_camt",
    "path": "addons/enterprise/account_bank_statement_import_camt",
    "name": "Import CAMT Bank Statement",
    "summary": null,
    "version": null,
    "category": "Accounting",
    "depends": "account_bank_statement_import",
    "auto_install": false,
    "application": null,
    "license": "OEEL-1",
    "has_qweb": false,
    "has_data": true
  },
  {
    "module": "account_bank_statement_import_csv",
    "path": "addons/enterprise/account_bank_statement_import_csv",
    "name": "Import CSV Bank Statement",
    "summary": null,
    "version": "1.0",
    "category": "Accounting",
    "depends": "account_bank_statement_import,base_import",
    "auto_install": true,
    "application": null,
    "license": "OEEL-1",
    "has_qweb": false,
    "has_data": true
  },
  {
    "module": "account_bank_statement_import_ofx",
    "path": "addons/enterprise/account_bank_statement_import_ofx",
    "name": "Import OFX Bank Statement",
    "summary": null,
    "version": "1.0",
    "category": "Accounting",
    "depends": "account_bank_statement_import",
    "auto_install": true,
    "application": null,
    "license": "OEEL-1",
    "has_qweb": false,
    "has_data": true
  },
  {
    "module": "account_bank_statement_import_qif",
    "path": "addons/enterprise/account_bank_statement_import_qif",
    "name": "Import QIF Bank Statement",
    "summary": null,
    "version": "1.0",
    "category": "Accounting",
    "depends": "account_bank_statement_import",
    "auto_install": false,
    "application": null,
    "license": "OEEL-1",
    "has_qweb": false,
    "has_data": true
  },
  {
    "module": "account_batch_payment",
    "path": "addons/enterprise/account_batch_payment",
    "name": "Batch Payment",
    "summary": null,
    "version": "1.0",
    "category": "Accounting",
    "depends": "account",
    "auto_install": null,
    "application": null,
    "license": "OEEL-1",
    "has_qweb": true,
    "has_data": true
  },
  {
    "module": "account_budget",
    "path": "addons/enterprise/account_budget",
    "name": "Budget Management",
    "summary": null,
    "version": null,
    "category": "Accounting",
    "depends": "account",
    "auto_install": null,
    "application": null,
    "license": null,
    "has_qweb": false,
    "has_data": true
  },
  {
    "module": "account_deferred_revenue",
    "path": "addons/enterprise/account_deferred_revenue",
    "name": "Deferred Revenues",
    "summary": null,
    "version": "1.0",
    "category": "Accounting",
    "depends": "account_asset",
    "auto_install": null,
    "application": false,
    "license": "OEEL-1",
    "has_qweb": false,
    "has_data": true
  },
  {
    "module": "account_intrastat",
    "path": "addons/enterprise/account_intrastat",
    "name": "Intrastat Reports",
    "summary": null,
    "version": null,
    "category": "Accounting",
    "depends": "account_reports",
    "auto_install": null,
    "application": null,
    "license": null,
    "has_qweb": false,
    "has_data": true
  },
  {
    "module": "account_invoice_extract",
    "path": "addons/enterprise/account_invoice_extract",
    "name": "Account Invoice Extract",
    "summary": "Extract data from invoice scans to fill them automatically",
    "version": "1.0",
    "category": "Accounting",
    "depends": "account_accountant,iap,mail_enterprise",
    "auto_install": true,
    "application": null,
    "license": null,
    "has_qweb": false,
    "has_data": true
  },
  {
    "module": "account_online_sync",
    "path": "addons/enterprise/account_online_sync",
    "name": "account_online_sync",
    "summary": "\n        This module is used for Online bank synchronization.",
    "version": "2.0",
    "category": "Accounting",
    "depends": "account",
    "auto_install": true,
    "application": null,
    "license": "OEEL-1",
    "has_qweb": true,
    "has_data": true
  },
  {
    "module": "account_plaid",
    "path": "addons/enterprise/account_plaid",
    "name": "account_plaid",
    "summary": "\n        Use Plaid.com to retrieve bank statements",
    "version": "3.0",
    "category": "Accounting",
    "depends": "account_online_sync",
    "auto_install": true,
    "application": null,
    "license": "OEEL-1",
    "has_qweb": true,
    "has_data": true
  },
  {
    "module": "account_predictive_bills",
    "path": "addons/enterprise/account_predictive_bills",
    "name": "Predictive vendor bill data",
    "summary": null,
    "version": "1.0",
    "category": "Accounting",
    "depends": "account_accountant",
    "auto_install": true,
    "application": null,
    "license": null,
    "has_qweb": false,
    "has_data": true
  },
  {
    "module": "account_reports",
    "path": "addons/enterprise/account_reports",
    "name": "Accounting Reports",
    "summary": "View and create reports",
    "version": null,
    "category": "Accounting",
    "depends": "account_accountant",
    "auto_install": true,
    "application": null,
    "license": "OEEL-1",
    "has_qweb": true,
    "has_data": true
  },
  {
    "module": "account_reports_followup",
    "path": "addons/enterprise/account_reports_followup",
    "name": "Payment Follow-up Management",
    "summary": null,
    "version": "1.0",
    "category": "Accounting",
    "depends": "account,mail,account_reports",
    "auto_install": false,
    "application": null,
    "license": "OEEL-1",
    "has_qweb": true,
    "has_data": true
  },
  {
    "module": "account_sepa",
    "path": "addons/enterprise/account_sepa",
    "name": "SEPA Credit Transfer",
    "summary": "Export payments as SEPA Credit Transfer files",
    "version": "1.0",
    "category": "Accounting",
    "depends": "account_batch_payment,base_iban",
    "auto_install": null,
    "application": null,
    "license": "OEEL-1",
    "has_qweb": false,
    "has_data": true
  },
  {
    "module": "account_sepa_direct_debit",
    "path": "addons/enterprise/account_sepa_direct_debit",
    "name": "SEPA Direct Debit",
    "summary": "Collect payments from your customers through SEPA direct debit.",
    "version": null,
    "category": "Accounting",
    "depends": "base_iban,account_batch_payment",
    "auto_install": null,
    "application": null,
    "license": null,
    "has_qweb": false,
    "has_data": true
  },
  {
    "module": "account_taxcloud",
    "path": "addons/enterprise/account_taxcloud",
    "name": "Account TaxCloud",
    "summary": "TaxCloud make it easy for business to comply with sales tax law",
    "version": "1.0",
    "category": "Accounting",
    "depends": "l10n_us",
    "auto_install": true,
    "application": null,
    "license": "OEEL-1",
    "has_qweb": false,
    "has_data": true
  },
  {
    "module": "account_yodlee",
    "path": "addons/enterprise/account_yodlee",
    "name": "Yodlee",
    "summary": "Yodlee Finance",
    "version": "2.0",
    "category": "Accounting",
    "depends": "account_online_sync",
    "auto_install": true,
    "application": null,
    "license": "OEEL-1",
    "has_qweb": true,
    "has_data": true
  },
  {
    "module": "analytic_enterprise",
    "path": "addons/enterprise/analytic_enterprise",
    "name": "Analytic Accounting Enterprise",
    "summary": null,
    "version": "0.1",
    "category": "Hidden/Dependency",
    "depends": "web_grid,analytic,account",
    "auto_install": true,
    "application": null,
    "license": null,
    "has_qweb": false,
    "has_data": true
  },
  {
    "module": "barcodes_mobile",
    "path": "addons/enterprise/barcodes_mobile",
    "name": "Barcode in Mobile",
    "summary": "Barcode scan in Mobile",
    "version": "1.0",
    "category": "Mobile",
    "depends": "barcodes,web_mobile",
    "auto_install": true,
    "application": null,
    "license": "OEEL-1",
    "has_qweb": false,
    "has_data": true
  },
  {
    "module": "base_automation_hr_contract",
    "path": "addons/enterprise/base_automation_hr_contract",
    "name": "Automated Action based on Employee Contracts",
    "summary": null,
    "version": "1.0",
    "category": "Human Resources",
    "depends": "base_automation,hr_contract",
    "auto_install": true,
    "application": null,
    "license": null,
    "has_qweb": false,
    "has_data": true
  },
  {
    "module": "crm_enterprise",
    "path": "addons/enterprise/crm_enterprise",
    "name": "CRM enterprise",
    "summary": "Advanced features for CRM",
    "version": "1.0",
    "category": "Sales",
    "depends": "crm,web_dashboard,web_cohort",
    "auto_install": true,
    "application": false,
    "license": null,
    "has_qweb": false,
    "has_data": true
  },
  {
    "module": "currency_rate_live",
    "path": "addons/enterprise/currency_rate_live",
    "name": "Live Currency Exchange Rate",
    "summary": null,
    "version": "1.0",
    "category": "Accounting",
    "depends": "account",
    "auto_install": true,
    "application": null,
    "license": "OEEL-1",
    "has_qweb": false,
    "has_data": true
  },
  {
    "module": "delivery_barcode",
    "path": "addons/enterprise/delivery_barcode",
    "name": "Delivery Barcode Scanning",
    "summary": "Add barcode scanning facilities to Delivery.",
    "version": "1.0",
    "category": null,
    "depends": "stock_barcode,delivery",
    "auto_install": true,
    "application": null,
    "license": "OEEL-1",
    "has_qweb": false,
    "has_data": true
  },
  {
    "module": "delivery_bpost",
    "path": "addons/enterprise/delivery_bpost",
    "name": "bpost Shipping",
    "summary": null,
    "version": "1.0",
    "category": "Warehouse",
    "depends": "delivery,mail",
    "auto_install": null,
    "application": null,
    "license": "OEEL-1",
    "has_qweb": false,
    "has_data": true
  },
  {
    "module": "delivery_dhl",
    "path": "addons/enterprise/delivery_dhl",
    "name": "DHL Express Shipping",
    "summary": null,
    "version": "1.0",
    "category": "Warehouse",
    "depends": "delivery,mail",
    "auto_install": null,
    "application": null,
    "license": "OEEL-1",
    "has_qweb": false,
    "has_data": true
  },
  {
    "module": "delivery_easypost",
    "path": "addons/enterprise/delivery_easypost",
    "name": "Easypost Shipping",
    "summary": null,
    "version": "1.0",
    "category": "Warehouse",
    "depends": "delivery,mail",
    "auto_install": null,
    "application": null,
    "license": null,
    "has_qweb": false,
    "has_data": true
  },
  {
    "module": "delivery_fedex",
    "path": "addons/enterprise/delivery_fedex",
    "name": "Fedex Shipping",
    "summary": null,
    "version": "1.0",
    "category": "Warehouse",
    "depends": "delivery,mail",
    "auto_install": null,
    "application": null,
    "license": "OEEL-1",
    "has_qweb": false,
    "has_data": true
  },
  {
    "module": "delivery_ups",
    "path": "addons/enterprise/delivery_ups",
    "name": "UPS Shipping",
    "summary": null,
    "version": "1.0",
    "category": "Warehouse",
    "depends": "delivery,mail",
    "auto_install": null,
    "application": null,
    "license": "OEEL-1",
    "has_qweb": false,
    "has_data": true
  },
  {
    "module": "delivery_usps",
    "path": "addons/enterprise/delivery_usps",
    "name": "United States Postal Service (USPS) Shipping",
    "summary": null,
    "version": "1.0",
    "category": "Warehouse",
    "depends": "delivery,mail",
    "auto_install": null,
    "application": null,
    "license": "OEEL-1",
    "has_qweb": false,
    "has_data": true
  },
  {
    "module": "documents",
    "path": "addons/enterprise/documents",
    "name": "Documents",
    "summary": "Document management",
    "version": "1.0",
    "category": "Extra Tools",
    "depends": "base,mail,portal,web",
    "auto_install": null,
    "application": true,
    "license": null,
    "has_qweb": true,
    "has_data": true
  },
  {
    "module": "documents_account",
    "path": "addons/enterprise/documents_account",
    "name": "Documents - Accounting",
    "summary": "Invoices from Documents",
    "version": "1.0",
    "category": "Uncategorized",
    "depends": "documents,account",
    "auto_install": true,
    "application": null,
    "license": null,
    "has_qweb": false,
    "has_data": true
  },
  {
    "module": "documents_product",
    "path": "addons/enterprise/documents_product",
    "name": "Documents - Product",
    "summary": "Products from Documents",
    "version": "1.0",
    "category": "Uncategorized",
    "depends": "documents,product",
    "auto_install": true,
    "application": null,
    "license": null,
    "has_qweb": false,
    "has_data": true
  },
  {
    "module": "documents_project",
    "path": "addons/enterprise/documents_project",
    "name": "Documents - Projects",
    "summary": "Project from documents",
    "version": "1.0",
    "category": "Uncategorized",
    "depends": "documents,project",
    "auto_install": true,
    "application": null,
    "license": null,
    "has_qweb": false,
    "has_data": true
  },
  {
    "module": "documents_sign",
    "path": "addons/enterprise/documents_sign",
    "name": "Documents - Signatures",
    "summary": "Signature templates from Documents",
    "version": "1.0",
    "category": "Uncategorized",
    "depends": "documents,sign",
    "auto_install": true,
    "application": null,
    "license": null,
    "has_qweb": false,
    "has_data": true
  },
  {
    "module": "event_barcode",
    "path": "addons/enterprise/event_barcode",
    "name": "Event Barcode Scanning",
    "summary": "Add barcode scanning feature to event management.",
    "version": null,
    "category": "Tools",
    "depends": "barcodes,event",
    "auto_install": null,
    "application": null,
    "license": "OEEL-1",
    "has_qweb": true,
    "has_data": true
  },
  {
    "module": "event_barcode_mobile",
    "path": "addons/enterprise/event_barcode_mobile",
    "name": "Event Barcode in Mobile",
    "summary": "Event Barcode scan in Mobile",
    "version": "1.0",
    "category": "Mobile",
    "depends": "event_barcode,web_mobile",
    "auto_install": true,
    "application": null,
    "license": "OEEL-1",
    "has_qweb": true,
    "has_data": true
  },
  {
    "module": "event_enterprise",
    "path": "addons/enterprise/event_enterprise",
    "name": "Events Organization Add-on",
    "summary": "Displays cohort analysis on attendees.",
    "version": null,
    "category": "Marketing",
    "depends": "event,web_cohort",
    "auto_install": true,
    "application": null,
    "license": "OEEL-1",
    "has_qweb": false,
    "has_data": true
  },
  {
    "module": "helpdesk",
    "path": "addons/enterprise/helpdesk",
    "name": "Helpdesk",
    "summary": "Track help tickets",
    "version": "1.2",
    "category": "Helpdesk",
    "depends": "base_setup,mail,utm,rating,web_tour,resource,portal,digest",
    "auto_install": null,
    "application": true,
    "license": "OEEL-1",
    "has_qweb": true,
    "has_data": true
  },
  {
    "module": "helpdesk_sale_timesheet",
    "path": "addons/enterprise/helpdesk_sale_timesheet",
    "name": "Sell Helpdesk Timesheet",
    "summary": "Project, Helpdesk, Timesheet and Sale Orders",
    "version": null,
    "category": "Hidden",
    "depends": "helpdesk_timesheet,sale_timesheet",
    "auto_install": true,
    "application": null,
    "license": null,
    "has_qweb": false,
    "has_data": true
  },
  {
    "module": "helpdesk_timesheet",
    "path": "addons/enterprise/helpdesk_timesheet",
    "name": "Helpdesk Timesheet",
    "summary": "Project, Tasks, Timesheet",
    "version": null,
    "category": "Helpdesk",
    "depends": "helpdesk,hr_timesheet",
    "auto_install": null,
    "application": null,
    "license": null,
    "has_qweb": false,
    "has_data": true
  },
  {
    "module": "hr_appraisal",
    "path": "addons/enterprise/hr_appraisal",
    "name": "Appraisal",
    "summary": "Assess your employees",
    "version": "1.0",
    "category": "Human Resources",
    "depends": "hr,calendar,survey",
    "auto_install": null,
    "application": true,
    "license": "OEEL-1",
    "has_qweb": false,
    "has_data": true
  },
  {
    "module": "hr_contract_salary",
    "path": "addons/enterprise/hr_contract_salary",
    "name": "HR Contract Salary (Belgium)",
    "summary": "Salary Package Configurator",
    "version": null,
    "category": "Human Resource",
    "depends": "hr,website,hr_recruitment,l10n_be_hr_payroll_fleet,sign",
    "auto_install": null,
    "application": null,
    "license": null,
    "has_qweb": false,
    "has_data": true
  },
  {
    "module": "hr_holidays_gantt",
    "path": "addons/enterprise/hr_holidays_gantt",
    "name": "Leaves Gantt",
    "summary": "Gantt view for Leaves Dashboard",
    "version": "1.0",
    "category": "Human Resources",
    "depends": "hr_holidays,web_gantt",
    "auto_install": true,
    "application": null,
    "license": "OEEL-1",
    "has_qweb": false,
    "has_data": true
  },
  {
    "module": "inter_company_rules",
    "path": "addons/enterprise/inter_company_rules",
    "name": "Inter Company Module for Sale/Purchase Orders and Invoices",
    "summary": "Intercompany SO/PO/INV rules",
    "version": "1.1",
    "category": "Productivity",
    "depends": "sale_management,purchase_stock,sale_stock",
    "auto_install": false,
    "application": null,
    "license": "OEEL-1",
    "has_qweb": false,
    "has_data": true
  },
  {
    "module": "iot",
    "path": "addons/enterprise/iot",
    "name": "Internet of Things",
    "summary": "Basic models and helpers to support Internet of Things.",
    "version": null,
    "category": "Tools",
    "depends": "mail,web",
    "auto_install": false,
    "application": true,
    "license": null,
    "has_qweb": false,
    "has_data": true
  },
  {
    "module": "l10n_ar_reports",
    "path": "addons/enterprise/l10n_ar_reports",
    "name": "Argentina - Accounting Reports",
    "summary": null,
    "version": "1.1",
    "category": "Accounting",
    "depends": "l10n_ar,account_reports",
    "auto_install": true,
    "application": null,
    "license": "OEEL-1",
    "has_qweb": false,
    "has_data": true
  },
  {
    "module": "l10n_at_reports",
    "path": "addons/enterprise/l10n_at_reports",
    "name": "Austria - Accounting",
    "summary": null,
    "version": "1.0",
    "category": "Accounting",
    "depends": "l10n_at,account_reports",
    "auto_install": true,
    "application": null,
    "license": "OEEL-1",
    "has_qweb": false,
    "has_data": true
  },
  {
    "module": "l10n_au_aba",
    "path": "addons/enterprise/l10n_au_aba",
    "name": "ABA Credit Transfer",
    "summary": "Export payments as ABA Credit Transfer files",
    "version": "1.0",
    "category": "Accounting &amp; Finance",
    "depends": "account_batch_payment,l10n_au",
    "auto_install": true,
    "application": null,
    "license": "OEEL-1",
    "has_qweb": false,
    "has_data": true
  },
  {
    "module": "l10n_au_reports",
    "path": "addons/enterprise/l10n_au_reports",
    "name": "Australian - Accounting Reports",
    "summary": null,
    "version": "1.1",
    "category": "Accounting",
    "depends": "l10n_au,account_reports",
    "auto_install": true,
    "application": null,
    "license": "OEEL-1",
    "has_qweb": false,
    "has_data": true
  },
  {
    "module": "l10n_be_coda",
    "path": "addons/enterprise/l10n_be_coda",
    "name": "Belgium - Import Bank CODA Statements",
    "summary": null,
    "version": "2.1",
    "category": "Accounting",
    "depends": "account_accountant,l10n_be,account_bank_statement_import,base_iban",
    "auto_install": true,
    "application": null,
    "license": "OEEL-1",
    "has_qweb": false,
    "has_data": true
  },
  {
    "module": "l10n_be_intrastat",
    "path": "addons/enterprise/l10n_be_intrastat",
    "name": "Belgian Intrastat Declaration",
    "summary": null,
    "version": null,
    "category": "Accounting",
    "depends": "l10n_be,account_intrastat",
    "auto_install": true,
    "application": null,
    "license": null,
    "has_qweb": false,
    "has_data": true
  },
  {
    "module": "l10n_be_intrastat_2019",
    "path": "addons/enterprise/l10n_be_intrastat_2019",
    "name": "Belgian Intrastat Declaration - Complement for 2019",
    "summary": null,
    "version": null,
    "category": "Accounting",
    "depends": "l10n_be_intrastat",
    "auto_install": true,
    "application": null,
    "license": null,
    "has_qweb": false,
    "has_data": true
  },
  {
    "module": "l10n_be_reports",
    "path": "addons/enterprise/l10n_be_reports",
    "name": "Belgium - Accounting Reports",
    "summary": null,
    "version": "1.1",
    "category": "Accounting",
    "depends": "l10n_be,account_reports",
    "auto_install": true,
    "application": null,
    "license": "OEEL-1",
    "has_qweb": false,
    "has_data": true
  },
  {
    "module": "l10n_bo_reports",
    "path": "addons/enterprise/l10n_bo_reports",
    "name": "Bolivia - Accounting Reports",
    "summary": null,
    "version": "1.1",
    "category": "Accounting",
    "depends": "l10n_bo,account_reports",
    "auto_install": true,
    "application": null,
    "license": "OEEL-1",
    "has_qweb": false,
    "has_data": true
  },
  {
    "module": "l10n_br_reports",
    "path": "addons/enterprise/l10n_br_reports",
    "name": "Brazilian - Accounting Reports",
    "summary": null,
    "version": "1.1",
    "category": "Accounting",
    "depends": "l10n_br,account_reports",
    "auto_install": true,
    "application": null,
    "license": "OEEL-1",
    "has_qweb": false,
    "has_data": true
  },
  {
    "module": "l10n_ca_check_printing",
    "path": "addons/enterprise/l10n_ca_check_printing",
    "name": "Canadian Checks Layout",
    "summary": "Print CA Checks",
    "version": "1.0",
    "category": "Accounting",
    "depends": "account_check_printing,l10n_ca",
    "auto_install": true,
    "application": null,
    "license": "OEEL-1",
    "has_qweb": false,
    "has_data": true
  },
  {
    "module": "l10n_ch_reports",
    "path": "addons/enterprise/l10n_ch_reports",
    "name": "Switzerland - Accounting Reports",
    "summary": null,
    "version": "1.1",
    "category": "Accounting",
    "depends": "l10n_ch,account_reports",
    "auto_install": true,
    "application": null,
    "license": "OEEL-1",
    "has_qweb": false,
    "has_data": true
  },
  {
    "module": "l10n_cl_reports",
    "path": "addons/enterprise/l10n_cl_reports",
    "name": "Chile - Accounting Reports",
    "summary": null,
    "version": "1.1",
    "category": "Accounting",
    "depends": "l10n_cl,account_reports",
    "auto_install": true,
    "application": null,
    "license": "OEEL-1",
    "has_qweb": false,
    "has_data": true
  },
  {
    "module": "l10n_co_edi",
    "path": "addons/enterprise/l10n_co_edi",
    "name": "Electronic invoicing for Colombia with Carvajal",
    "summary": "Colombian Localization for EDI documents",
    "version": "0.1",
    "category": "Accounting",
    "depends": "account,l10n_co",
    "auto_install": null,
    "application": null,
    "license": null,
    "has_qweb": false,
    "has_data": true
  },
  {
    "module": "l10n_co_reports",
    "path": "addons/enterprise/l10n_co_reports",
    "name": "Colombian - Accounting Reports",
    "summary": null,
    "version": "1.1",
    "category": "Accounting",
    "depends": "l10n_co,account_reports",
    "auto_install": true,
    "application": null,
    "license": "OEEL-1",
    "has_qweb": false,
    "has_data": true
  },
  {
    "module": "l10n_de_reports",
    "path": "addons/enterprise/l10n_de_reports",
    "name": "Germany - Accounting Reports",
    "summary": null,
    "version": "1.1",
    "category": "Accounting",
    "depends": "l10n_de,account_reports",
    "auto_install": true,
    "application": null,
    "license": "OEEL-1",
    "has_qweb": false,
    "has_data": true
  },
  {
    "module": "l10n_do_reports",
    "path": "addons/enterprise/l10n_do_reports",
    "name": "Dominican Republic - Accounting",
    "summary": null,
    "version": "1.0",
    "category": "Accounting",
    "depends": "l10n_do,account_reports",
    "auto_install": true,
    "application": null,
    "license": "OEEL-1",
    "has_qweb": false,
    "has_data": true
  },
  {
    "module": "l10n_es_real_estates",
    "path": "addons/enterprise/l10n_es_real_estates",
    "name": "l10n_es_real_estates",
    "summary": null,
    "version": "0.1",
    "category": "Accounting",
    "depends": "l10n_es_reports",
    "auto_install": null,
    "application": null,
    "license": null,
    "has_qweb": false,
    "has_data": true
  },
  {
    "module": "l10n_es_reports",
    "path": "addons/enterprise/l10n_es_reports",
    "name": "Spain - Accounting (PGCE 2008) Reports",
    "summary": null,
    "version": "4.1",
    "category": "Accounting",
    "depends": "l10n_es,account_reports",
    "auto_install": true,
    "application": null,
    "license": "OEEL-1",
    "has_qweb": false,
    "has_data": true
  },
  {
    "module": "l10n_et_reports",
    "path": "addons/enterprise/l10n_et_reports",
    "name": "Ethiopia - Accounting Reports",
    "summary": null,
    "version": "1.1",
    "category": "Accounting",
    "depends": "l10n_et,account_reports",
    "auto_install": true,
    "application": null,
    "license": "OEEL-1",
    "has_qweb": false,
    "has_data": true
  },
  {
    "module": "l10n_fr_reports",
    "path": "addons/enterprise/l10n_fr_reports",
    "name": "France - Accounting Reports",
    "summary": null,
    "version": "1.1",
    "category": "Accounting",
    "depends": "l10n_fr,account_reports",
    "auto_install": true,
    "application": null,
    "license": "OEEL-1",
    "has_qweb": false,
    "has_data": true
  },
  {
    "module": "l10n_gr_reports",
    "path": "addons/enterprise/l10n_gr_reports",
    "name": "Greece - Accounting Reports",
    "summary": null,
    "version": "1.1",
    "category": "Accounting",
    "depends": "l10n_gr,account_reports",
    "auto_install": true,
    "application": null,
    "license": "OEEL-1",
    "has_qweb": false,
    "has_data": true
  },
  {
    "module": "l10n_hr_reports",
    "path": "addons/enterprise/l10n_hr_reports",
    "name": "Croatia - RRIF 2012 COA - Accounting Reports",
    "summary": null,
    "version": "1.1",
    "category": "Accounting",
    "depends": "l10n_hr,account_reports",
    "auto_install": true,
    "application": null,
    "license": "OEEL-1",
    "has_qweb": false,
    "has_data": true
  },
  {
    "module": "l10n_hu_reports",
    "path": "addons/enterprise/l10n_hu_reports",
    "name": "Hungarian - Accounting Reports",
    "summary": null,
    "version": "1.1",
    "category": "Accounting",
    "depends": "l10n_hu,account_reports",
    "auto_install": true,
    "application": null,
    "license": "OEEL-1",
    "has_qweb": false,
    "has_data": true
  },
  {
    "module": "l10n_in_reports",
    "path": "addons/enterprise/l10n_in_reports",
    "name": "Indian - Accounting Reports",
    "summary": null,
    "version": "1.1",
    "category": "Accounting",
    "depends": "l10n_in,account_reports",
    "auto_install": true,
    "application": null,
    "license": "OEEL-1",
    "has_qweb": false,
    "has_data": true
  },
  {
    "module": "l10n_jp_reports",
    "path": "addons/enterprise/l10n_jp_reports",
    "name": "Japan - Accounting Reports",
    "summary": null,
    "version": "1.1",
    "category": "Accounting",
    "depends": "l10n_jp,account_reports",
    "auto_install": true,
    "application": null,
    "license": "OEEL-1",
    "has_qweb": false,
    "has_data": true
  },
  {
    "module": "l10n_lu_reports",
    "path": "addons/enterprise/l10n_lu_reports",
    "name": "Luxembourg - Accounting Reports",
    "summary": null,
    "version": "1.1",
    "category": "Accounting",
    "depends": "l10n_lu,account_reports",
    "auto_install": true,
    "application": null,
    "license": "OEEL-1",
    "has_qweb": false,
    "has_data": true
  },
  {
    "module": "l10n_ma_reports",
    "path": "addons/enterprise/l10n_ma_reports",
    "name": "Maroc - Accounting Reports",
    "summary": null,
    "version": "1.1",
    "category": "Accounting",
    "depends": "l10n_ma,account_reports",
    "auto_install": true,
    "application": null,
    "license": "OEEL-1",
    "has_qweb": false,
    "has_data": true
  },
  {
    "module": "l10n_mx_edi",
    "path": "addons/enterprise/l10n_mx_edi",
    "name": "EDI for Mexico",
    "summary": "Mexican Localization for EDI documents",
    "version": "0.1",
    "category": "Hidden",
    "depends": "account,account_cancel,base_vat,base_address_extended,document,base_address_city",
    "auto_install": false,
    "application": null,
    "license": null,
    "has_qweb": false,
    "has_data": true
  },
  {
    "module": "l10n_mx_edi_customs",
    "path": "addons/enterprise/l10n_mx_edi_customs",
    "name": "Odoo Mexico Localization for Invoice with customs Number",
    "summary": "\n        Generate Electronic Invoice with Customs Number\n    ",
    "version": "0.1",
    "category": "Hidden",
    "depends": "l10n_mx_edi",
    "auto_install": null,
    "application": null,
    "license": "OEEL-1",
    "has_qweb": false,
    "has_data": true
  },
  {
    "module": "l10n_mx_edi_external_trade",
    "path": "addons/enterprise/l10n_mx_edi_external_trade",
    "name": "EDI External Trade Complement for Mexico",
    "summary": "External Trade Complement for the Mexican localization",
    "version": "0.1",
    "category": "Hidden",
    "depends": "l10n_mx_edi",
    "auto_install": false,
    "application": null,
    "license": null,
    "has_qweb": false,
    "has_data": true
  },
  {
    "module": "l10n_mx_edi_landing",
    "path": "addons/enterprise/l10n_mx_edi_landing",
    "name": "Odoo Mexico Localization for Stock/Landing",
    "summary": "\n        Generate Electronic Invoice with Customs Number\n    ",
    "version": "11.0.1.0.0",
    "category": "Hidden",
    "depends": "stock_landed_costs,sale_management,l10n_mx_edi_customs",
    "auto_install": null,
    "application": null,
    "license": null,
    "has_qweb": false,
    "has_data": true
  },
  {
    "module": "l10n_mx_edi_payment",
    "path": "addons/enterprise/l10n_mx_edi_payment",
    "name": "EDI Payment",
    "summary": "Mexican Localization for EDI documents",
    "version": "0.1",
    "category": "Hidden",
    "depends": "l10n_mx_edi",
    "auto_install": true,
    "application": null,
    "license": null,
    "has_qweb": false,
    "has_data": false
  },
  {
    "module": "l10n_mx_edi_payment_bank",
    "path": "addons/enterprise/l10n_mx_edi_payment_bank",
    "name": "Bank account payment to Mexico",
    "summary": "Bank account in the payments",
    "version": "0.1",
    "category": "Hidden",
    "depends": "l10n_mx_edi",
    "auto_install": true,
    "application": null,
    "license": null,
    "has_qweb": false,
    "has_data": true
  },
  {
    "module": "l10n_mx_reports",
    "path": "addons/enterprise/l10n_mx_reports",
    "name": "Odoo Mexican Localization Reports",
    "summary": "\n        Electronic accounting reports\n            - COA\n            - Trial Balance\n        DIOT Report\n    ",
    "version": "10.0.1.0.0",
    "category": "Accounting",
    "depends": "account_reports,l10n_mx",
    "auto_install": true,
    "application": null,
    "license": "OEEL-1",
    "has_qweb": false,
    "has_data": true
  },
  {
    "module": "l10n_mx_tax_cash_basis",
    "path": "addons/enterprise/l10n_mx_tax_cash_basis",
    "name": "Tax Cash Basis Entries at Payment Date",
    "summary": "\n    Properly create the Journal Entries on Tax Cash basis when using foreign\n    currencies the Tax must be set at date of payment\n    ",
    "version": "0.1",
    "category": "Accounting",
    "depends": "l10n_mx_edi",
    "auto_install": true,
    "application": null,
    "license": "OEEL-1",
    "has_qweb": false,
    "has_data": false
  },
  {
    "module": "l10n_nl_intrastat",
    "path": "addons/enterprise/l10n_nl_intrastat",
    "name": "Netherlands Intrastat Declaration",
    "summary": null,
    "version": null,
    "category": "Localization",
    "depends": "l10n_nl,account_intrastat",
    "auto_install": true,
    "application": null,
    "license": null,
    "has_qweb": false,
    "has_data": true
  },
  {
    "module": "l10n_nl_reports",
    "path": "addons/enterprise/l10n_nl_reports",
    "name": "Netherlands - Accounting Reports",
    "summary": null,
    "version": "1.5",
    "category": "Accounting",
    "depends": "l10n_nl,account_reports",
    "auto_install": true,
    "application": null,
    "license": "OEEL-1",
    "has_qweb": false,
    "has_data": true
  },
  {
    "module": "l10n_no_reports",
    "path": "addons/enterprise/l10n_no_reports",
    "name": "Norway - Accounting Reports",
    "summary": null,
    "version": "1.1",
    "category": "Accounting",
    "depends": "l10n_no,account_reports",
    "auto_install": true,
    "application": null,
    "license": "OEEL-1",
    "has_qweb": false,
    "has_data": true
  },
  {
    "module": "l10n_pl_reports",
    "path": "addons/enterprise/l10n_pl_reports",
    "name": "Poland - Accounting Reports",
    "summary": null,
    "version": "1.1",
    "category": "Accounting",
    "depends": "l10n_pl,account_reports",
    "auto_install": true,
    "application": null,
    "license": "OEEL-1",
    "has_qweb": false,
    "has_data": true
  },
  {
    "module": "l10n_ro_reports",
    "path": "addons/enterprise/l10n_ro_reports",
    "name": "Romania - Accounting Reports",
    "summary": null,
    "version": "1.1",
    "category": "Accounting",
    "depends": "l10n_ro,account_reports",
    "auto_install": true,
    "application": null,
    "license": "OEEL-1",
    "has_qweb": false,
    "has_data": true
  },
  {
    "module": "l10n_sg_reports",
    "path": "addons/enterprise/l10n_sg_reports",
    "name": "Singapore - Accounting Reports",
    "summary": null,
    "version": "1.1",
    "category": "Accounting",
    "depends": "l10n_sg,account_reports",
    "auto_install": true,
    "application": null,
    "license": "OEEL-1",
    "has_qweb": false,
    "has_data": true
  },
  {
    "module": "l10n_si_reports",
    "path": "addons/enterprise/l10n_si_reports",
    "name": "Slovenian - Accounting Reports",
    "summary": null,
    "version": "1.1",
    "category": "Accounting",
    "depends": "l10n_si,account_reports",
    "auto_install": true,
    "application": null,
    "license": "OEEL-1",
    "has_qweb": false,
    "has_data": true
  },
  {
    "module": "l10n_th_reports",
    "path": "addons/enterprise/l10n_th_reports",
    "name": "Thailand - Accounting Reports",
    "summary": null,
    "version": "1.1",
    "category": "Accounting",
    "depends": "l10n_th,account_reports",
    "auto_install": true,
    "application": null,
    "license": "OEEL-1",
    "has_qweb": false,
    "has_data": true
  },
  {
    "module": "l10n_uk_reports",
    "path": "addons/enterprise/l10n_uk_reports",
    "name": "UK - Accounting Reports",
    "summary": null,
    "version": "1.1",
    "category": "Accounting",
    "depends": "l10n_uk,account_reports",
    "auto_install": true,
    "application": null,
    "license": "OEEL-1",
    "has_qweb": false,
    "has_data": true
  },
  {
    "module": "l10n_uk_reports_hmrc",
    "path": "addons/enterprise/l10n_uk_reports_hmrc",
    "name": "UK - Accounting Reports to HMRC",
    "summary": null,
    "version": "1.1",
    "category": "Accounting",
    "depends": "l10n_uk_reports",
    "auto_install": true,
    "application": null,
    "license": "OEEL-1",
    "has_qweb": false,
    "has_data": true
  },
  {
    "module": "l10n_us_check_printing",
    "path": "addons/enterprise/l10n_us_check_printing",
    "name": "US Checks Layout",
    "summary": "Print US Checks",
    "version": "1.0",
    "category": "Accounting",
    "depends": "account_check_printing,l10n_us",
    "auto_install": true,
    "application": null,
    "license": "OEEL-1",
    "has_qweb": false,
    "has_data": true
  },
  {
    "module": "l10n_us_reports",
    "path": "addons/enterprise/l10n_us_reports",
    "name": "US - Accounting Reports",
    "summary": null,
    "version": "1.0",
    "category": "Accounting",
    "depends": "l10n_us,account_reports",
    "auto_install": true,
    "application": null,
    "license": "OEEL-1",
    "has_qweb": false,
    "has_data": true
  },
  {
    "module": "l10n_uy_reports",
    "path": "addons/enterprise/l10n_uy_reports",
    "name": "Uruguay - Accounts Reports",
    "summary": null,
    "version": "1.1",
    "category": "Accounting",
    "depends": "l10n_uy,account_reports",
    "auto_install": true,
    "application": null,
    "license": "OEEL-1",
    "has_qweb": false,
    "has_data": true
  },
  {
    "module": "l10n_vn_reports",
    "path": "addons/enterprise/l10n_vn_reports",
    "name": "Vietnam - Accounting Reports",
    "summary": null,
    "version": "1.1",
    "category": "Accounting",
    "depends": "l10n_vn,account_reports",
    "auto_install": true,
    "application": null,
    "license": "OEEL-1",
    "has_qweb": false,
    "has_data": true
  },
  {
    "module": "mail_enterprise",
    "path": "addons/enterprise/mail_enterprise",
    "name": "Mail Enterprise",
    "summary": null,
    "version": null,
    "category": "Discuss",
    "depends": "mail",
    "auto_install": true,
    "application": null,
    "license": "OEEL-1",
    "has_qweb": true,
    "has_data": true
  },
  {
    "module": "mail_github",
    "path": "addons/enterprise/mail_github",
    "name": "Github Integration with Discuss",
    "summary": null,
    "version": null,
    "category": "Discuss",
    "depends": "mail",
    "auto_install": null,
    "application": null,
    "license": "OEEL-1",
    "has_qweb": false,
    "has_data": true
  },
  {
    "module": "marketing_automation",
    "path": "addons/enterprise/marketing_automation",
    "name": "Marketing Automation",
    "summary": "Build automated mailing campaigns",
    "version": "1.0",
    "category": "Marketing",
    "depends": "mass_mailing",
    "auto_install": null,
    "application": true,
    "license": "OEEL-1",
    "has_qweb": false,
    "has_data": true
  },
  {
    "module": "mass_mailing_themes",
    "path": "addons/enterprise/mass_mailing_themes",
    "name": "Mass Mailing Themes",
    "summary": "Design gorgeous mails",
    "version": "1.0",
    "category": "Marketing",
    "depends": "mass_mailing",
    "auto_install": true,
    "application": null,
    "license": "OEEL-1",
    "has_qweb": false,
    "has_data": true
  },
  {
    "module": "mrp_account",
    "path": "addons/enterprise/mrp_account",
    "name": "Accounting - MRP",
    "summary": "Analytic accounting in Manufacturing",
    "version": "1.0",
    "category": "Manufacturing",
    "depends": "mrp,stock_account",
    "auto_install": true,
    "application": null,
    "license": "OEEL-1",
    "has_qweb": false,
    "has_data": true
  },
  {
    "module": "mrp_maintenance",
    "path": "addons/enterprise/mrp_maintenance",
    "name": "Maintenance - MRP",
    "summary": "Schedule and manage maintenance on machine and tools.",
    "version": "1.0",
    "category": "Manufacturing",
    "depends": "mrp_workorder,maintenance",
    "auto_install": true,
    "application": null,
    "license": "OEEL-1",
    "has_qweb": false,
    "has_data": true
  },
  {
    "module": "mrp_mps",
    "path": "addons/enterprise/mrp_mps",
    "name": "Master Production Schedule",
    "summary": "Master Production Schedule",
    "version": "1.0",
    "category": "Manufacturing",
    "depends": "mrp,purchase",
    "auto_install": null,
    "application": false,
    "license": "OEEL-1",
    "has_qweb": true,
    "has_data": true
  },
  {
    "module": "mrp_plm",
    "path": "addons/enterprise/mrp_plm",
    "name": "Product Lifecycle Management (PLM)",
    "summary": "Manage engineering change orders on products, bills of material and routings",
    "version": "1.0",
    "category": "Manufacturing",
    "depends": "mrp",
    "auto_install": null,
    "application": true,
    "license": "OEEL-1",
    "has_qweb": true,
    "has_data": true
  },
  {
    "module": "mrp_workorder",
    "path": "addons/enterprise/mrp_workorder",
    "name": "MRP II",
    "summary": "Work Orders, Planing, Stock Reports.",
    "version": "1.0",
    "category": "Manufacturing",
    "depends": "quality,mrp,barcodes",
    "auto_install": null,
    "application": false,
    "license": "OEEL-1",
    "has_qweb": true,
    "has_data": true
  },
  {
    "module": "mrp_zebra",
    "path": "addons/enterprise/mrp_zebra",
    "name": "Zebra printers integration for MRP",
    "summary": "\n        Zebra printers integration for mrp module",
    "version": "1.0",
    "category": "mrp",
    "depends": "stock_zebra,quality_mrp_iot",
    "auto_install": true,
    "application": null,
    "license": null,
    "has_qweb": false,
    "has_data": true
  },
  {
    "module": "ocn_client",
    "path": "addons/enterprise/ocn_client",
    "name": "Odoo Cloud Notification Client (OCN)",
    "summary": "Allow push notification to devices",
    "version": "1.0",
    "category": "Tool",
    "depends": "iap,mail",
    "auto_install": true,
    "application": null,
    "license": null,
    "has_qweb": false,
    "has_data": true
  },
  {
    "module": "pos_blackbox_be",
    "path": "addons/enterprise/pos_blackbox_be",
    "name": "Belgian Registered Cash Register",
    "summary": "Implements the registered cash system, adhering to guidelines by FPS Finance.",
    "version": "1.0",
    "category": "Point of Sale",
    "depends": "pos_restaurant,l10n_be,web_enterprise",
    "auto_install": false,
    "application": null,
    "license": "OEEL-1",
    "has_qweb": true,
    "has_data": true
  },
  {
    "module": "pos_enterprise",
    "path": "addons/enterprise/pos_enterprise",
    "name": "Point of Sale enterprise",
    "summary": "Advanced features for PoS",
    "version": null,
    "category": "Point of Sale",
    "depends": "web_enterprise,point_of_sale",
    "auto_install": true,
    "application": null,
    "license": null,
    "has_qweb": false,
    "has_data": true
  },
  {
    "module": "pos_iot",
    "path": "addons/enterprise/pos_iot",
    "name": "",
    "summary": "Link your PoS configuration with an IoT Box",
    "version": "1.0",
    "category": "Point of Sale",
    "depends": "point_of_sale,iot",
    "auto_install": true,
    "application": null,
    "license": "OEEL-1",
    "has_qweb": false,
    "has_data": true
  },
  {
    "module": "pos_loyalty",
    "path": "addons/enterprise/pos_loyalty",
    "name": "Loyalty Program",
    "summary": "Loyalty Program for the Point of Sale ",
    "version": "1.0",
    "category": "Point of Sale",
    "depends": "point_of_sale",
    "auto_install": false,
    "application": null,
    "license": "OEEL-1",
    "has_qweb": true,
    "has_data": true
  },
  {
    "module": "pos_restaurant_iot",
    "path": "addons/enterprise/pos_restaurant_iot",
    "name": "",
    "summary": "Link your PoS configuration with an IoT Box for the restaurant",
    "version": "1.0",
    "category": "Point of Sale",
    "depends": "pos_restaurant,iot",
    "auto_install": true,
    "application": null,
    "license": "OEEL-1",
    "has_qweb": false,
    "has_data": true
  },
  {
    "module": "project_enterprise",
    "path": "addons/enterprise/project_enterprise",
    "name": "Project Enterprise",
    "summary": "Bridge module for project and enterprise",
    "version": "1.0",
    "category": "Project",
    "depends": "project",
    "auto_install": true,
    "application": null,
    "license": "OEEL-1",
    "has_qweb": false,
    "has_data": true
  },
  {
    "module": "project_forecast",
    "path": "addons/enterprise/project_forecast",
    "name": "Forecast",
    "summary": "Forecast your resources on project tasks",
    "version": "1.0",
    "category": "Project",
    "depends": "project,web_grid,hr",
    "auto_install": null,
    "application": true,
    "license": "OEEL-1",
    "has_qweb": false,
    "has_data": true
  },
  {
    "module": "project_timesheet_forecast",
    "path": "addons/enterprise/project_timesheet_forecast",
    "name": "Timesheet and Forecast",
    "summary": "Compare timesheets and forecasts",
    "version": "1.0",
    "category": "Hidden",
    "depends": "hr_timesheet,project_forecast",
    "auto_install": true,
    "application": null,
    "license": null,
    "has_qweb": false,
    "has_data": true
  },
  {
    "module": "project_timesheet_forecast_sale",
    "path": "addons/enterprise/project_timesheet_forecast_sale",
    "name": "Compare timesheets and forecast for your projects",
    "summary": null,
    "version": "1.0",
    "category": "Project",
    "depends": "project_forecast,sale_timesheet",
    "auto_install": true,
    "application": null,
    "license": "OEEL-1",
    "has_qweb": false,
    "has_data": true
  },
  {
    "module": "project_timesheet_synchro",
    "path": "addons/enterprise/project_timesheet_synchro",
    "name": "Synchronization with the external timesheet application",
    "summary": null,
    "version": "1.0",
    "category": "Project",
    "depends": "hr_timesheet",
    "auto_install": true,
    "application": null,
    "license": "OEEL-1",
    "has_qweb": true,
    "has_data": true
  },
  {
    "module": "purchase_mrp_workorder_quality",
    "path": "addons/enterprise/purchase_mrp_workorder_quality",
    "name": "Full Traceability Report Demo Data",
    "summary": "Full Traceability Report Demo Data",
    "version": "1.0",
    "category": "Manufacturing",
    "depends": "purchase_mrp,quality_mrp_workorder,purchase_stock",
    "auto_install": null,
    "application": false,
    "license": "OEEL-1",
    "has_qweb": false,
    "has_data": false
  },
  {
    "module": "quality",
    "path": "addons/enterprise/quality",
    "name": "Quality Base",
    "summary": "Basic Feature for Quality",
    "version": "1.0",
    "category": "Manufacturing",
    "depends": "stock,decimal_precision",
    "auto_install": null,
    "application": false,
    "license": "OEEL-1",
    "has_qweb": false,
    "has_data": true
  },
  {
    "module": "quality_control",
    "path": "addons/enterprise/quality_control",
    "name": "Quality",
    "summary": "Control the quality of your products",
    "version": "1.0",
    "category": "Manufacturing",
    "depends": "quality",
    "auto_install": null,
    "application": true,
    "license": "OEEL-1",
    "has_qweb": false,
    "has_data": true
  },
  {
    "module": "quality_iot",
    "path": "addons/enterprise/quality_iot",
    "name": "Quality Steps with IoT",
    "summary": "Quality steps and IoT devices",
    "version": null,
    "category": "Tools",
    "depends": "iot,quality_control",
    "auto_install": true,
    "application": null,
    "license": null,
    "has_qweb": false,
    "has_data": true
  },
  {
    "module": "quality_mrp",
    "path": "addons/enterprise/quality_mrp",
    "name": "MRP features for Quality Control",
    "summary": "Quality Management with MRP",
    "version": "1.0",
    "category": "Manufacturing",
    "depends": "quality_control,mrp",
    "auto_install": true,
    "application": null,
    "license": "OEEL-1",
    "has_qweb": false,
    "has_data": true
  },
  {
    "module": "quality_mrp_iot",
    "path": "addons/enterprise/quality_mrp_iot",
    "name": "IoT features for Work Order Quality Control",
    "summary": "Quality steps in MRP work orders with IoT devices",
    "version": "1.0",
    "category": "Manufacturing",
    "depends": "quality_mrp_workorder,iot",
    "auto_install": true,
    "application": null,
    "license": "OEEL-1",
    "has_qweb": false,
    "has_data": true
  },
  {
    "module": "quality_mrp_workorder",
    "path": "addons/enterprise/quality_mrp_workorder",
    "name": "MRP features for Quality Control",
    "summary": "Quality Management with MRP",
    "version": "1.0",
    "category": "Manufacturing",
    "depends": "quality_control,mrp_workorder,barcodes",
    "auto_install": true,
    "application": null,
    "license": "OEEL-1",
    "has_qweb": false,
    "has_data": true
  },
  {
    "module": "sale_account_taxcloud",
    "path": "addons/enterprise/sale_account_taxcloud",
    "name": "Account TaxCloud - Sale",
    "summary": "",
    "version": null,
    "category": "Accounting",
    "depends": "account_taxcloud,sale",
    "auto_install": true,
    "application": null,
    "license": "OEEL-1",
    "has_qweb": false,
    "has_data": true
  },
  {
    "module": "sale_coupon",
    "path": "addons/enterprise/sale_coupon",
    "name": "Sale Coupon",
    "summary": "Allows to use discount coupons in sales orders",
    "version": "1.0",
    "category": "Sales",
    "depends": "sale_management",
    "auto_install": null,
    "application": null,
    "license": null,
    "has_qweb": false,
    "has_data": true
  },
  {
    "module": "sale_coupon_delivery",
    "path": "addons/enterprise/sale_coupon_delivery",
    "name": "Sale Coupon Delivery",
    "summary": "Allows to offer free shippings in coupon reward",
    "version": "1.0",
    "category": "Sales",
    "depends": "sale_coupon,delivery",
    "auto_install": true,
    "application": null,
    "license": null,
    "has_qweb": false,
    "has_data": false
  },
  {
    "module": "sale_ebay",
    "path": "addons/enterprise/sale_ebay",
    "name": "eBay Connector",
    "summary": "\n  Publish your products on eBay",
    "version": "1.0",
    "category": "Sales",
    "depends": "base,sale_management,stock,delivery,document",
    "auto_install": null,
    "application": false,
    "license": "OEEL-1",
    "has_qweb": true,
    "has_data": true
  },
  {
    "module": "sale_enterprise",
    "path": "addons/enterprise/sale_enterprise",
    "name": "Sale enterprise",
    "summary": "Advanced Features for Sale Management",
    "version": "1.0",
    "category": "Sales",
    "depends": "sale,web_dashboard",
    "auto_install": true,
    "application": false,
    "license": null,
    "has_qweb": false,
    "has_data": true
  },
  {
    "module": "sale_intrastat",
    "path": "addons/enterprise/sale_intrastat",
    "name": "Sale Intrastat",
    "summary": null,
    "version": null,
    "category": "Accounting",
    "depends": "sale,account_intrastat",
    "auto_install": true,
    "application": null,
    "license": null,
    "has_qweb": false,
    "has_data": false
  },
  {
    "module": "sale_subscription",
    "path": "addons/enterprise/sale_subscription",
    "name": "Subscriptions",
    "summary": "Generate recurring invoices and manage renewals",
    "version": "1.1",
    "category": "Sales",
    "depends": "account_deferred_revenue,sale_management,portal,web_cohort,rating,base_automation",
    "auto_install": null,
    "application": true,
    "license": "OEEL-1",
    "has_qweb": false,
    "has_data": true
  },
  {
    "module": "sale_subscription_asset",
    "path": "addons/enterprise/sale_subscription_asset",
    "name": "Deferred Revenues Management for Subscriptions",
    "summary": null,
    "version": "1.0",
    "category": "Sales",
    "depends": "sale_subscription,account_deferred_revenue",
    "auto_install": true,
    "application": null,
    "license": "OEEL-1",
    "has_qweb": false,
    "has_data": true
  },
  {
    "module": "sale_subscription_dashboard",
    "path": "addons/enterprise/sale_subscription_dashboard",
    "name": "Sale Subscription Dashboard",
    "summary": null,
    "version": "1.0",
    "category": "Accounting",
    "depends": "sale_subscription,sale_subscription_asset",
    "auto_install": true,
    "application": null,
    "license": "OEEL-1",
    "has_qweb": true,
    "has_data": true
  },
  {
    "module": "sign",
    "path": "addons/enterprise/sign",
    "name": "Sign",
    "summary": "Send documents to sign online and handle filled copies",
    "version": "1.0",
    "category": "Document Management",
    "depends": "mail,document,portal,sms",
    "auto_install": null,
    "application": true,
    "license": "OEEL-1",
    "has_qweb": true,
    "has_data": true
  },
  {
    "module": "snailmail_account_reports_followup",
    "path": "addons/enterprise/snailmail_account_reports_followup",
    "name": "Snail Mail Follow-Up",
    "summary": "Extension to send follow-up documents by post",
    "version": "1.0",
    "category": "Tools",
    "depends": "snailmail,account_reports_followup",
    "auto_install": true,
    "application": null,
    "license": "OEEL-1",
    "has_qweb": true,
    "has_data": true
  },
  {
    "module": "stock_account_enterprise",
    "path": "addons/enterprise/stock_account_enterprise",
    "name": "Stock account enterprise",
    "summary": "Advanced features for stock_account",
    "version": "1.0",
    "category": "Stock",
    "depends": "stock_account,web_dashboard",
    "auto_install": true,
    "application": false,
    "license": null,
    "has_qweb": false,
    "has_data": true
  },
  {
    "module": "stock_barcode",
    "path": "addons/enterprise/stock_barcode",
    "name": "Barcode",
    "summary": "Use barcode scanners to process logistics operations",
    "version": "1.0",
    "category": "Warehouse",
    "depends": "barcodes,stock,web_tour",
    "auto_install": null,
    "application": true,
    "license": "OEEL-1",
    "has_qweb": true,
    "has_data": true
  },
  {
    "module": "stock_barcode_mobile",
    "path": "addons/enterprise/stock_barcode_mobile",
    "name": "Stock Barcode in Mobile",
    "summary": "Stock Barcode scan in Mobile",
    "version": "1.0",
    "category": "Mobile",
    "depends": "stock_barcode,web_mobile",
    "auto_install": true,
    "application": null,
    "license": "OEEL-1",
    "has_qweb": true,
    "has_data": true
  },
  {
    "module": "stock_enterprise",
    "path": "addons/enterprise/stock_enterprise",
    "name": "Stock enterprise",
    "summary": "Advanced features for Stock",
    "version": "1.0",
    "category": "Stock",
    "depends": "stock,web_dashboard,web_cohort",
    "auto_install": true,
    "application": false,
    "license": null,
    "has_qweb": false,
    "has_data": true
  },
  {
    "module": "stock_intrastat",
    "path": "addons/enterprise/stock_intrastat",
    "name": "Stock Intrastat",
    "summary": null,
    "version": null,
    "category": "Stock",
    "depends": "stock_account,account_intrastat",
    "auto_install": true,
    "application": null,
    "license": null,
    "has_qweb": false,
    "has_data": true
  },
  {
    "module": "test_marketing_automation",
    "path": "addons/enterprise/test_marketing_automation",
    "name": "Marketing Automation Tests",
    "summary": "Test Suits for Automated Marketing Campaigns",
    "version": "1.0",
    "category": "Hidden",
    "depends": "marketing_automation,test_mail",
    "auto_install": null,
    "application": false,
    "license": null,
    "has_qweb": false,
    "has_data": false
  },
  {
    "module": "timesheet_grid",
    "path": "addons/enterprise/timesheet_grid",
    "name": "Timesheets",
    "summary": "Timesheet Validation and Grid View",
    "version": "1.0",
    "category": null,
    "depends": "web_grid,hr_timesheet",
    "auto_install": true,
    "application": true,
    "license": "OEEL-1",
    "has_qweb": false,
    "has_data": true
  },
  {
    "module": "timesheet_grid_sale",
    "path": "addons/enterprise/timesheet_grid_sale",
    "name": "Sales Timesheet: Grid Support",
    "summary": "Configure timesheet invoicing",
    "version": "0.1",
    "category": "Hidden",
    "depends": "sale_timesheet,timesheet_grid",
    "auto_install": true,
    "application": null,
    "license": "OEEL-1",
    "has_qweb": false,
    "has_data": true
  },
  {
    "module": "voip",
    "path": "addons/enterprise/voip",
    "name": "VOIP",
    "summary": "\n        Make calls using a VOIP system",
    "version": "2.0",
    "category": "Sales",
    "depends": "base,mail,web,phone_validation",
    "auto_install": null,
    "application": true,
    "license": "OEEL-1",
    "has_qweb": true,
    "has_data": true
  },
  {
    "module": "voip_onsip",
    "path": "addons/enterprise/voip_onsip",
    "name": "VOIP OnSIP",
    "summary": null,
    "version": "1.0",
    "category": "Hidden",
    "depends": "voip",
    "auto_install": null,
    "application": false,
    "license": "OEEL-1",
    "has_qweb": false,
    "has_data": true
  },
  {
    "module": "web_cohort",
    "path": "addons/enterprise/web_cohort",
    "name": "Cohort View",
    "summary": "Basic Cohort view for odoo",
    "version": null,
    "category": null,
    "depends": "web",
    "auto_install": true,
    "application": null,
    "license": "OEEL-1",
    "has_qweb": true,
    "has_data": true
  },
  {
    "module": "web_dashboard",
    "path": "addons/enterprise/web_dashboard",
    "name": "web_dashboard",
    "summary": null,
    "version": "1.0",
    "category": "Hidden",
    "depends": "web",
    "auto_install": true,
    "application": null,
    "license": null,
    "has_qweb": true,
    "has_data": true
  },
  {
    "module": "web_enterprise",
    "path": "addons/enterprise/web_enterprise",
    "name": "Web Enterprise",
    "summary": null,
    "version": "1.0",
    "category": "Hidden",
    "depends": "web",
    "auto_install": true,
    "application": null,
    "license": "OEEL-1",
    "has_qweb": true,
    "has_data": true
  },
  {
    "module": "web_gantt",
    "path": "addons/enterprise/web_gantt",
    "name": "Web Gantt",
    "summary": null,
    "version": "2.0",
    "category": "Hidden",
    "depends": "web",
    "auto_install": true,
    "application": null,
    "license": "OEEL-1",
    "has_qweb": true,
    "has_data": true
  },
  {
    "module": "web_grid",
    "path": "addons/enterprise/web_grid",
    "name": "Grid View",
    "summary": "Basic 2D Grid view for odoo",
    "version": "0.1",
    "category": null,
    "depends": "web",
    "auto_install": true,
    "application": null,
    "license": "OEEL-1",
    "has_qweb": true,
    "has_data": true
  },
  {
    "module": "web_mobile",
    "path": "addons/enterprise/web_mobile",
    "name": "Mobile",
    "summary": "Odoo Mobile Core module",
    "version": "1.0",
    "category": "Mobile",
    "depends": "web_settings_dashboard",
    "auto_install": true,
    "application": null,
    "license": "OEEL-1",
    "has_qweb": true,
    "has_data": true
  },
  {
    "module": "web_studio",
    "path": "addons/enterprise/web_studio",
    "name": "Studio",
    "summary": "Create and customize your Odoo apps",
    "version": "1.0",
    "category": "Technical Settings",
    "depends": "base_automation,base_import_module,mail,web,web_enterprise,web_editor",
    "auto_install": null,
    "application": true,
    "license": "OEEL-1",
    "has_qweb": true,
    "has_data": true
  },
  {
    "module": "website_calendar",
    "path": "addons/enterprise/website_calendar",
    "name": "Appointments",
    "summary": "Schedule appointments with clients",
    "version": "1.0",
    "category": "Website",
    "depends": "calendar_sms,website_enterprise,hr",
    "auto_install": false,
    "application": true,
    "license": "OEEL-1",
    "has_qweb": false,
    "has_data": true
  },
  {
    "module": "website_crm_score",
    "path": "addons/enterprise/website_crm_score",
    "name": "Lead Scoring",
    "summary": null,
    "version": "1.0",
    "category": "Sales",
    "depends": "base,sales_team,website_crm,crm_enterprise",
    "auto_install": null,
    "application": false,
    "license": "OEEL-1",
    "has_qweb": false,
    "has_data": true
  },
  {
    "module": "website_delivery_ups",
    "path": "addons/enterprise/website_delivery_ups",
    "name": "UPS: Bill My Account",
    "summary": "Bill to your UPS account number",
    "version": null,
    "category": "Warehouse",
    "depends": "delivery_ups,website_sale_delivery",
    "auto_install": true,
    "application": null,
    "license": null,
    "has_qweb": false,
    "has_data": true
  },
  {
    "module": "website_enterprise",
    "path": "addons/enterprise/website_enterprise",
    "name": "Website Enterprise",
    "summary": "Get the enterprise look and feel",
    "version": null,
    "category": "Technical Settings",
    "depends": "website",
    "auto_install": true,
    "application": null,
    "license": "OEEL-1",
    "has_qweb": false,
    "has_data": true
  },
  {
    "module": "website_form_editor",
    "path": "addons/enterprise/website_form_editor",
    "name": "Form Builder",
    "summary": "Build custom web forms",
    "version": "1.0",
    "category": "Website",
    "depends": "website_enterprise,website_form",
    "auto_install": false,
    "application": null,
    "license": "OEEL-1",
    "has_qweb": false,
    "has_data": true
  },
  {
    "module": "website_helpdesk",
    "path": "addons/enterprise/website_helpdesk",
    "name": "Website Helpdesk",
    "summary": "Bridge module for helpdesk modules using the website.",
    "version": null,
    "category": "Hidden",
    "depends": "helpdesk,website",
    "auto_install": null,
    "application": null,
    "license": "OEEL-1",
    "has_qweb": false,
    "has_data": true
  },
  {
    "module": "website_helpdesk_form",
    "path": "addons/enterprise/website_helpdesk_form",
    "name": "Online Ticket Submission",
    "summary": "Qualify helpdesk queries with a website form",
    "version": null,
    "category": "Website",
    "depends": "website_form_editor,website_helpdesk",
    "auto_install": null,
    "application": null,
    "license": "OEEL-1",
    "has_qweb": false,
    "has_data": true
  },
  {
    "module": "website_helpdesk_forum",
    "path": "addons/enterprise/website_helpdesk_forum",
    "name": "Helpdesk: Knowledge Base",
    "summary": "Knowledge base for helpdesk based on Odoo Forum",
    "version": null,
    "category": "Helpdesk",
    "depends": "website_forum,website_helpdesk",
    "auto_install": true,
    "application": null,
    "license": "OEEL-1",
    "has_qweb": false,
    "has_data": true
  },
  {
    "module": "website_helpdesk_livechat",
    "path": "addons/enterprise/website_helpdesk_livechat",
    "name": "Website IM Livechat Helpdesk",
    "summary": "Ticketing, Support, Livechat",
    "version": null,
    "category": "Helpdesk",
    "depends": "website_helpdesk,website_livechat",
    "auto_install": true,
    "application": null,
    "license": "OEEL-1",
    "has_qweb": false,
    "has_data": true
  },
  {
    "module": "website_helpdesk_slides",
    "path": "addons/enterprise/website_helpdesk_slides",
    "name": "Website Slides Helpdesk",
    "summary": "Ticketing, Support, Slides",
    "version": null,
    "category": "Helpdesk",
    "depends": "website_helpdesk,website_slides",
    "auto_install": true,
    "application": null,
    "license": "OEEL-1",
    "has_qweb": false,
    "has_data": true
  },
  {
    "module": "website_sale_account_taxcloud",
    "path": "addons/enterprise/website_sale_account_taxcloud",
    "name": "Account TaxCloud - Ecommerce",
    "summary": "",
    "version": null,
    "category": "Accounting",
    "depends": "account_taxcloud,website_sale",
    "auto_install": true,
    "application": null,
    "license": "OEEL-1",
    "has_qweb": false,
    "has_data": false
  },
  {
    "module": "website_sale_coupon",
    "path": "addons/enterprise/website_sale_coupon",
    "name": "Coupons & Promotions for eCommerce",
    "summary": "Use coupon & promotion programs in your eCommerce store",
    "version": "1.0",
    "category": "Website",
    "depends": "website_sale,sale_coupon",
    "auto_install": true,
    "application": null,
    "license": null,
    "has_qweb": false,
    "has_data": true
  },
  {
    "module": "website_sale_dashboard",
    "path": "addons/enterprise/website_sale_dashboard",
    "name": "Website Sales Dashboard",
    "summary": "Get a new dashboard view in the Website App",
    "version": "1.0",
    "category": "Technical Settings",
    "depends": "website_sale,web_dashboard",
    "auto_install": true,
    "application": null,
    "license": null,
    "has_qweb": true,
    "has_data": true
  },
  {
    "module": "website_sale_taxcloud_delivery",
    "path": "addons/enterprise/website_sale_taxcloud_delivery",
    "name": "TaxCloud and Delivery - Ecommerce",
    "summary": "Compute taxes with TaxCloud after online delivery computation.",
    "version": null,
    "category": "Accounting &amp; Finance",
    "depends": "website_sale_delivery,website_sale_account_taxcloud",
    "auto_install": true,
    "application": null,
    "license": "OEEL-1",
    "has_qweb": false,
    "has_data": false
  },
  {
    "module": "website_studio",
    "path": "addons/enterprise/website_studio",
    "name": "Website Studio",
    "summary": "Display Website Elements in Studio",
    "version": "1.0",
    "category": "Technical Settings",
    "depends": "web_studio,website_form_editor",
    "auto_install": true,
    "application": null,
    "license": "OEEL-1",
    "has_qweb": true,
    "has_data": true
  },
  {
    "module": "website_twitter_wall",
    "path": "addons/enterprise/website_twitter_wall",
    "name": "Twitter Wall",
    "summary": "Pretty Way to Display Tweets for Event",
    "version": null,
    "category": "Website",
    "depends": "website_twitter",
    "auto_install": null,
    "application": null,
    "license": "OEEL-1",
    "has_qweb": false,
    "has_data": true
  }
]